{
  "path": "/",
  "blocks": [
    {
      "_template": "ContentBlock",
      "content": "## Umor bis\n\nWe are the **University of Surrey Computing Society**, or **CompSoc**. We host academic events in the field of Computer Science, organising and managing professional events around our field, and social events primarily for CompSci students to have fun.\n\n[**Click here to join us, it’s free!**](https://surreycompsoc.com/join/)\n\nIf you’d like to interact with us, the best bet is to message our [Facebook page](https://www.facebook.com/ComputingSoc). We’d be happy to answer any questions you have about our society, or indeed about Computer Science at Surrey. You can also get in touch with us about opportunities for our Society to get involved with."
    }
  ],
  "hero": {
    "headline": "CompSoc",
    "textline": "amazing",
    "ctas": [
      {
        "label": "Read The Blog",
        "link": "/blog",
        "primary": true,
        "arrow": true
      },
      {
        "label": "Contact Us",
        "link": "/contact",
        "arrow": false,
        "primary": false
      }
    ],
    "image": "../images/undefined",
    "large": false
  },
  "displayTitle": false,
  "title": "Home"
}